{
  "$type": "Scenario, Assembly-CSharp",
  "Elements": [
    {
      "$type": "OverlayPicture, Assembly-CSharp",
      "EffectID": "111",
      "PictureID": "111"
    },
    {
      "$type": "Dialogue, Assembly-CSharp",
      "CharacterID": "Mono",
      "Lines": [
        {
          "$type": "Line, Assembly-CSharp",
          "EmotionID": "Smile",
          "Sentence": "xxx"
        },
        {
          "$type": "Line, Assembly-CSharp",
          "EmotionID": "Smile",
          "Sentence": "xxx\n"
        },
        {
          "$type": "Line, Assembly-CSharp",
          "EmotionID": "Smile",
          "Sentence": "xxx"
        }
      ]
    },
    {
      "$type": "ItemModify, Assembly-CSharp",
      "IsGain": true,
      "Id": "1111",
      "Amount": 11
    }
  ]
}